puzzle_solvers/__init__.py
puzzle_solvers/elimination.py
puzzle_solvers/version.py
puzzle_solvers/demos/__init__.py
puzzle_solvers/demos/elimination.py
puzzle_solvers/demos/elimination_zebra.py
puzzle_solvers-0.0.1b3.data/data/CHANGELOG
puzzle_solvers-0.0.1b3.data/data/LICENSE
puzzle_solvers-0.0.1b3.data/data/README.md
puzzle_solvers-0.0.1b3.dist-info/LICENSE
puzzle_solvers-0.0.1b3.dist-info/METADATA
puzzle_solvers-0.0.1b3.dist-info/WHEEL
puzzle_solvers-0.0.1b3.dist-info/top_level.txt
puzzle_solvers-0.0.1b3.dist-info/RECORD
