Metadata-Version: 2.1
Name: puzzle-solvers
Version: 0.0.1b3
Summary: Package of tools for solving logic puzzles
Home-page: https://gitlab.com/madphysicist/puzzle-solvers
Author: Joseph R. Fox-Rabinovitz
Author-email: jfoxrabinovitz@gmail.com
Maintainer: Joseph R. Fox-Rabinovitz
Maintainer-email: jfoxrabinovitz@gmail.com
License: MIT
Project-URL: Bugs, https://gitlab.com/madphysicist/puzzle-solvers/-/issues
Project-URL: Documentation, https://puzzle-solvers.readthedocs.io/en/latest/
Classifier: Development Status :: 2 - Pre-Alpha
Classifier: Intended Audience :: Education
Classifier: Intended Audience :: Other Audience
Classifier: License :: OSI Approved :: MIT License
Classifier: Operating System :: Microsoft :: Windows
Classifier: Operating System :: POSIX :: Linux
Classifier: Operating System :: Unix
Classifier: Operating System :: MacOS
Classifier: Programming Language :: Python
Classifier: Programming Language :: Python :: 3 :: Only
Classifier: Programming Language :: Python :: 3.6
Classifier: Programming Language :: Python :: 3.7
Classifier: Programming Language :: Python :: 3.8
Classifier: Programming Language :: Python :: 3.9
Classifier: Programming Language :: Python :: 3.10
Classifier: Topic :: Games/Entertainment :: Puzzle Games
Provides: puzzle_solvers
License-File: LICENSE
Requires-Dist: numpy (>=1.10.0)
Provides-Extra: mpl
Requires-Dist: matplotlib (>=2.0) ; extra == 'mpl'
